MANIFEST.in
README.rst
setup.cfg
setup.py
bin/compose_diff
compose_diff/__init__.py
compose_diff.egg-info/PKG-INFO
compose_diff.egg-info/SOURCES.txt
compose_diff.egg-info/dependency_links.txt
compose_diff.egg-info/not-zip-safe
compose_diff.egg-info/requires.txt
compose_diff.egg-info/top_level.txt
features/format.feature
features/instances.feature
features/versions.feature