Metadata-Version: 1.1
Name: compose-diff
Version: 0.3.0
Summary: diff docker-compose files
Home-page: http://github.com/funkwerk/compose_diff
Author: Stefan Rohe
Author-email: UNKNOWN
License: MIT
Keywords: docker-compose diff docker yml
Platform: UNKNOWN
Classifier: License :: OSI Approved :: MIT License
Classifier: Programming Language :: Python :: 3
Classifier: Topic :: Software Development
Classifier: Environment :: Console
Classifier: Operating System :: OS Independent
